MANIFEST.in
README.rst
setup.py
alcohol/__init__.py
alcohol.egg-info/PKG-INFO
alcohol.egg-info/SOURCES.txt
alcohol.egg-info/dependency_links.txt
alcohol.egg-info/requires.txt
alcohol.egg-info/top_level.txt
alcohol/mixins/__init__.py
alcohol/mixins/sqlalchemy.py
alcohol/rbac/__init__.py
alcohol/rbac/sqlalchemy.py