Metadata-Version: 1.0
Name: alcohol
Version: 0.4
Summary: Handles user authentication, in a way.
Home-page: http://github.com/mbr/alcohol
Author: Marc Brinkmann
Author-email: git@marcbrinkmann.de
License: MIT
Platform: UNKNOWN
